llama_find/__init__.py
llama_find/api.py
llama_find/mlx_compat.py
llama_find/web_server.py
llama_find/agents/__init__.py
llama_find/agents/agent.py
llama_find/agents/function_calling.py
llama_find/agents/tools.py
llama_find/utils/__init__.py
llama_find/utils/es_integration.py
llama_find/utils/query_expander.py
llama_find/utils/result_ranker.py
llamafind_llamasearch-0.1.0.dist-info/METADATA
llamafind_llamasearch-0.1.0.dist-info/WHEEL
llamafind_llamasearch-0.1.0.dist-info/licenses/LICENSE
llamafind_llamasearch-0.1.0.dist-info/RECORD
