Metadata-Version: 2.4
Name: llamafind-llamasearch
Version: 0.1.0
Summary: Base search engine integration and utilities for the LlamaAI Ecosystem
Project-URL: Homepage, https://github.com/yourusername/llama-find
Project-URL: Bug Tracker, https://github.com/yourusername/llama-find/issues
Project-URL: Documentation, https://yourusername.github.io/llama-find/
Author-email: llamafind-llamasearch <nikjois@llamasearch.ai>
License: MIT License
License-File: LICENSE
Classifier: Development Status :: 4 - Beta
Classifier: Intended Audience :: Developers
Classifier: License :: OSI Approved :: MIT License
Classifier: Programming Language :: Python :: 3
Classifier: Programming Language :: Python :: 3.8
Classifier: Programming Language :: Python :: 3.9
Classifier: Programming Language :: Python :: 3.10
Classifier: Programming Language :: Python :: 3.11
Classifier: Topic :: Scientific/Engineering :: Artificial Intelligence
Classifier: Topic :: Software Development :: Libraries :: Python Modules
Requires-Python: >=3.8
Requires-Dist: beautifulsoup4>=4.12.0
Requires-Dist: duckduckgo-search>=2.9.0
Requires-Dist: fastapi>=0.95.0
Requires-Dist: httpx>=0.24.0
Requires-Dist: loguru>=0.7.0
Provides-Extra: dev
Requires-Dist: black>=23.3.0; extra == 'dev'
Requires-Dist: isort>=5.12.0; extra == 'dev'
Requires-Dist: mypy>=1.2.0; extra == 'dev'
Requires-Dist: pre-commit>=3.3.1; extra == 'dev'
Requires-Dist: pytest-cov>=4.1.0; extra == 'dev'
Requires-Dist: pytest>=7.3.1; extra == 'dev'
Requires-Dist: ruff>=0.0.260; extra == 'dev'
Provides-Extra: docs
Requires-Dist: mkdocs-material>=9.1.6; extra == 'docs'
Requires-Dist: mkdocs>=1.4.2; extra == 'docs'
Requires-Dist: mkdocstrings[python]>=0.20.0; extra == 'docs'
